saftool/cache.py
saftool/date.py
saftool/encrypt.py
saftool/fo.py
saftool/global_var.py
saftool/jobs.py
saftool/log.py
saftool/maths.py
saftool/simple_request.py
saftool/tool.py
saftool/wrap.py
saftool-0.2.7.5.dist-info/LICENSE
saftool-0.2.7.5.dist-info/WHEEL
saftool-0.2.7.5.dist-info/METADATA
saftool-0.2.7.5.dist-info/RECORD
