Metadata-Version: 2.1
Name: saftool
Version: 0.2.7.5
Summary: 
Home-page: https://github.com/Asdil/saftool
License: MIT
Author: Asdil Fibrizo
Author-email: jpl4job@126.com
Requires-Python: >=3.6,<4.0
Classifier: License :: OSI Approved :: MIT License
Classifier: Programming Language :: Python :: 3
Classifier: Programming Language :: Python :: 3.10
Classifier: Programming Language :: Python :: 3.6
Classifier: Programming Language :: Python :: 3.7
Classifier: Programming Language :: Python :: 3.8
Classifier: Programming Language :: Python :: 3.9
Requires-Dist: joblib (>=1.0.1,<2.0.0)
Requires-Dist: py7zr (>=0.17.2,<0.18.0)
Requires-Dist: python-dateutil (>=2.8.1,<3.0.0)
Requires-Dist: requests (>=2.24.0,<3.0.0)
Requires-Dist: tqdm (>=4.59.0,<5.0.0)
Project-URL: Repository, https://github.com/Asdil/saftool
